tootnotify/__init__.py
tootnotify/tootnotify.py
tootnotify-1.0.0rc1.dist-info/LICENSE
tootnotify-1.0.0rc1.dist-info/METADATA
tootnotify-1.0.0rc1.dist-info/WHEEL
tootnotify-1.0.0rc1.dist-info/entry_points.txt
tootnotify-1.0.0rc1.dist-info/top_level.txt
tootnotify-1.0.0rc1.dist-info/RECORD
