Metadata-Version: 2.1
Name: tootnotify
Version: 1.0.0rc1
Summary: Command line tool to send DM notifications to a mastodon user.
Author-email: "Jorge A. Duarte" <babetoduarte@gmail.com>
Project-URL: Homepage, https://github.com/babetoduarte/TootNotify
Project-URL: Bug Tracker, https://github.com/babetoduarte/TootNotify/issues
Keywords: mastodon,notification
Classifier: Development Status :: 4 - Beta
Classifier: Programming Language :: Python :: 3
Classifier: License :: OSI Approved :: GNU General Public License v3 (GPLv3)
Classifier: Operating System :: OS Independent
Requires-Python: >=3.7
License-File: LICENSE
Requires-Dist: mastodon.py (>=1.8.0)
